fantasy_scout/__init__.py
fantasy_scout/cli_functions.py
fantasy_scout/api/__init__.py
fantasy_scout/api/fpl_api.py
fantasy_scout/api/player_cache.py
fantasy_scout/building_functions/__init__.py
fantasy_scout/building_functions/lp_max_score.py
fantasy_scout/entities/__init__.py
fantasy_scout/entities/player.py
fantasy_scout/entities/team.py
fantasy_scout/ranking_functions/__init__.py
fantasy_scout/ranking_functions/points_per_game.py
fantasy_scout/ranking_functions/rach_rank.py
fantasy_scout/utility/__init__.py
fantasy_scout/utility/build_class_for_json.py
fplscout-0.1.1.dist-info/METADATA
fplscout-0.1.1.dist-info/RECORD
fplscout-0.1.1.dist-info/WHEEL
fplscout-0.1.1.dist-info/entry_points.txt
fplscout-0.1.1.dist-info/top_level.txt
tests/__init__.py
tests/test_fantasy_scout.py
