Metadata-Version: 2.1
Name: fplscout
Version: 0.1.1
Summary: Picks good teams for the UK FPL Fantasy Football game
Home-page: https://github.com/rach-sharp/fpl-scout
Author: Rachel Sharp
Author-email: rachelsharp.dev@gmail.com
License: MIT License
Keywords: football
Platform: UNKNOWN
Requires-Dist: clint
Requires-Dist: requests
Requires-Dist: pulp
